[
  {
    "path": "posts/About Me/",
    "title": "About Me",
    "description": "That's right, who is François Fokan ?",
    "author": [
      {
        "name": "François Fokan",
        "url": {}
      }
    ],
    "date": "2021-04-12",
    "categories": [],
    "preview": "posts/About Me/image/UMons.png",
    "last_modified": "2021-04-12T15:02:24+02:00",
    "preview_width": 373,
    "preview_height": 135
  },
  {
    "path": "posts/Conclusion/",
    "title": "Conclusion",
    "description": "Here we are at the end of this Blog",
    "author": [
      {
        "name": "François Fokan",
        "url": {}
      }
    ],
    "date": "2021-04-12",
    "categories": [],
    "preview": {},
    "last_modified": "2021-04-12T15:02:38+02:00"
  },
  {
    "path": "posts/Bibliography/",
    "title": "Bibliography",
    "description": "All sources used",
    "author": [
      {
        "name": "François Fokan",
        "url": {}
      }
    ],
    "date": "2021-04-09",
    "categories": [],
    "preview": {},
    "last_modified": "2021-04-09T14:08:43+02:00"
  },
  {
    "path": "posts/Introduction/",
    "title": "Introduction",
    "description": "Dear reader, welcome to my blog",
    "author": [
      {
        "name": "François Fokan",
        "url": {}
      }
    ],
    "date": "2021-04-09",
    "categories": [],
    "preview": {},
    "last_modified": "2021-04-12T15:02:53+02:00"
  },
  {
    "path": "posts/M.E.A.L/",
    "title": "My English Activity Log (M.E.A.L.)",
    "description": "All about my progress in English.",
    "author": [
      {
        "name": "François Fokan",
        "url": {}
      }
    ],
    "date": "2021-04-09",
    "categories": [
      "English for Science",
      "M.E.A.L."
    ],
    "preview": "posts/M.E.A.L/image/speak1.png",
    "last_modified": "2021-04-09T14:10:38+02:00",
    "preview_width": 572,
    "preview_height": 545
  },
  {
    "path": "posts/Seventh Article Analysis/",
    "title": "Seventh Article Analysis : Aging and ailing lab Chimps are still at center of fight for Sanctuary",
    "description": "The N.I.H. refuses to move 39 chimpanzees from a research center to a sanctuary",
    "author": [
      {
        "name": "François Fokan",
        "url": {}
      }
    ],
    "date": "2021-03-13",
    "categories": [],
    "preview": "posts/Seventh Article Analysis/images/chimp.jpg",
    "last_modified": "2021-04-12T15:01:07+02:00"
  },
  {
    "path": "posts/Sixth Article Analysis/",
    "title": "Sixth Article Analysis : Monkeys, like humans, persist at tasks they've already invested in",
    "description": "Studying this phenomenon in animals can teach us about how their minds and ours work",
    "author": [
      {
        "name": "François Fokan",
        "url": {}
      }
    ],
    "date": "2021-03-02",
    "categories": [],
    "preview": "posts/Sixth Article Analysis/images/capucin.jpg",
    "last_modified": "2021-04-12T19:22:58+02:00"
  },
  {
    "path": "posts/Fifth Artcile Analysis/",
    "title": "Fifth Article Analysis : A crowded mountain can make Silverback Gorillas more violent",
    "description": "Gorillas are highly sociable animals – up to a point",
    "author": [
      {
        "name": "François Fokan",
        "url": {}
      }
    ],
    "date": "2021-02-04",
    "categories": [],
    "preview": "posts/Fifth Artcile Analysis/image/gorille.jpeg",
    "last_modified": "2021-04-12T19:22:47+02:00"
  },
  {
    "path": "posts/Fourth Article Analysis/",
    "title": "Fourth Article Analysis : Monkeys may share a key grammar-related skill with humans",
    "description": "A capacity for recursion evolved early in primate evolution, a contested study suggests",
    "author": [
      {
        "name": "François Fokan",
        "url": {}
      }
    ],
    "date": "2020-12-08",
    "categories": [],
    "preview": "posts/Fourth Article Analysis/image/monkey.jpg",
    "last_modified": "2021-04-12T19:21:12+02:00"
  },
  {
    "path": "posts/Third Article Analysis/",
    "title": "Third Article Analysis : Coppery Titi monkeys do not deceive their partners",
    "description": "In most species there is some proportion of offspring that is not sired by their social father",
    "author": [
      {
        "name": "François Fokan",
        "url": {}
      }
    ],
    "date": "2020-11-30",
    "categories": [],
    "preview": "posts/Third Article Analysis/image/Coppery.jpg",
    "last_modified": "2021-04-12T19:19:49+02:00"
  },
  {
    "path": "posts/Second Article Analysis/",
    "title": "Second Article Analysis : Conservation: Bridge of hope for world's rarest primate",
    "description": "Swinging through the treetops comes naturally for gibbons",
    "author": [
      {
        "name": "François Fokan",
        "url": {}
      }
    ],
    "date": "2020-11-24",
    "categories": [],
    "preview": "posts/Second Article Analysis/Images/gibbon.jpg",
    "last_modified": "2021-04-12T19:18:25+02:00"
  },
  {
    "path": "posts/Graphic Description/",
    "title": "Graphic Description",
    "description": "In this article, I treat of the **sea urchin biometry**. I chose this dataset because it has a large number of variables (19). \nThe sea urchins studied have two origins: one part comes from ***culture***, and the other from ***fishery***.",
    "author": [
      {
        "name": "François Fokan",
        "url": {}
      }
    ],
    "date": "2020-11-18",
    "categories": [],
    "preview": "posts/Graphic Description/graphicdescription_files/figure-html5/unnamed-chunk-1-1.png",
    "last_modified": "2020-11-18T14:32:00+01:00",
    "preview_width": 1248,
    "preview_height": 768
  },
  {
    "path": "posts/First Article Analysis/",
    "title": "First Article Analysis : Animals use social distancing to avoid disease",
    "description": "Lobsters, birds and some primates use quarantine to ward off infections",
    "author": [
      {
        "name": "François Fokan",
        "url": {}
      }
    ],
    "date": "2020-10-24",
    "categories": [],
    "preview": "posts/First Article Analysis/images/mandrills.jpg",
    "last_modified": "2021-04-12T19:16:46+02:00"
  },
  {
    "path": "posts/About Primates/",
    "title": "About Primates",
    "description": "It seems important to start at the beginning.",
    "author": [
      {
        "name": "François Fokan",
        "url": {}
      }
    ],
    "date": "2020-10-23",
    "categories": [],
    "preview": "posts/About Primates/images/chimpanzee.jpg",
    "last_modified": "2020-11-10T13:21:42+01:00"
  }
]
